mumax3c/__init__.py
mumax3c/compute.py
mumax3c/delete.py
mumax3c/drivers/__init__.py
mumax3c/drivers/driver.py
mumax3c/drivers/mindriver.py
mumax3c/drivers/relaxdriver.py
mumax3c/drivers/timedriver.py
mumax3c/mumax3/__init__.py
mumax3c/mumax3/mumax3.py
mumax3c/scripts/__init__.py
mumax3c/scripts/driver.py
mumax3c/scripts/energy.py
mumax3c/scripts/magnetisation.py
mumax3c/scripts/mesh.py
mumax3c/scripts/system.py
mumax3c/scripts/util.py
mumax3c/tests/__init__.py
mumax3c/tests/conftest.py
mumax3c/tests/test_init.py
mumax3c/tests/test_micromagnetictests.py
mumax3c/tests/test_mumax3.py
mumax3c/tests/test_util.py
mumax3c/tests/test_sample/test_mumax3.mx3
mumax3c/tests/test_sample/macrospin/drive-0/info.json
mumax3c/tests/test_sample/macrospin/drive-0/m0.omf
mumax3c/tests/test_sample/macrospin/drive-0/macrospin.mx3
mumax3c/tests/test_sample/macrospin/drive-0/mumax3_regions.omf
mumax3c-0.4.0.dist-info/licenses/LICENSE
mumax3c-0.4.0.dist-info/METADATA
mumax3c-0.4.0.dist-info/WHEEL
mumax3c-0.4.0.dist-info/top_level.txt
mumax3c-0.4.0.dist-info/RECORD
